libcomet/__init__.py
libcomet/sdk.py
libcomet-0.1.1.dist-info/DESCRIPTION.rst
libcomet-0.1.1.dist-info/METADATA
libcomet-0.1.1.dist-info/RECORD
libcomet-0.1.1.dist-info/WHEEL
libcomet-0.1.1.dist-info/metadata.json
libcomet-0.1.1.dist-info/top_level.txt
